Metadata-Version: 2.1
Name: microImage
Version: 2.3.1
Summary: Python module to open common types of image used in microscopy.
Home-page: https://github.com/vivien-walter/microImage
Author: Vivien WALTER
Author-email: walter.vivien@gmail.com
License: GPL3.0
Download-URL: https://github.com/vivien-walter/microImage/archive/v_2.3.1.tar.gz
Keywords: microscopy,image,open
Platform: UNKNOWN
Requires-Python: >=3.2
